markdown_to_blog/__init__.py
markdown_to_blog/config.py
markdown_to_blog/cli/__init__.py
markdown_to_blog/cli/auth.py
markdown_to_blog/cli/blog.py
markdown_to_blog/cli/convert.py
markdown_to_blog/cli/daemon.py
markdown_to_blog/cli/generate_post_from_airtable.py
markdown_to_blog/cli/gui.py
markdown_to_blog/cli/image.py
markdown_to_blog/cli/posting.py
markdown_to_blog/cli/publish.py
markdown_to_blog/cli/server.py
markdown_to_blog/gui/__init__.py
markdown_to_blog/gui/database.py
markdown_to_blog/gui/main_window.py
markdown_to_blog/gui/shell.py
markdown_to_blog/gui/models/__init__.py
markdown_to_blog/gui/models/publish_record.py
markdown_to_blog/gui/models/setting.py
markdown_to_blog/gui/models/workspace.py
markdown_to_blog/gui/utils/__init__.py
markdown_to_blog/gui/utils/publisher.py
markdown_to_blog/gui/views/__init__.py
markdown_to_blog/gui/views/ai_single_process_dialog.py
markdown_to_blog/gui/views/api_usage_dialog.py
markdown_to_blog/gui/views/blog_generator_dialog.py
markdown_to_blog/gui/views/publish_records_dialog.py
markdown_to_blog/gui/views/settings_dialog.py
markdown_to_blog/gui/views/workflow_dialog.py
markdown_to_blog/gui/views/workspace_dialog.py
markdown_to_blog/libs/__init__.py
markdown_to_blog/libs/airtable_getrow.py
markdown_to_blog/libs/airtable_post_generator.py
markdown_to_blog/libs/blog_generator.py
markdown_to_blog/libs/blogger.py
markdown_to_blog/libs/click_order.py
markdown_to_blog/libs/config_manager.py
markdown_to_blog/libs/daemon_client.py
markdown_to_blog/libs/daemon_server.py
markdown_to_blog/libs/exceptions.py
markdown_to_blog/libs/gemini.py
markdown_to_blog/libs/gemini_usage.py
markdown_to_blog/libs/i18n.py
markdown_to_blog/libs/markdown.py
markdown_to_blog/libs/protocol.json
markdown_to_blog/libs/web_to_markdown.py
markdown_to_blog/libs/image_uploader/__init__.py
markdown_to_blog/libs/image_uploader/config.py
markdown_to_blog/libs/image_uploader/exceptions.py
markdown_to_blog/libs/image_uploader/file_handler.py
markdown_to_blog-0.4.7.dist-info/METADATA
markdown_to_blog-0.4.7.dist-info/WHEEL
markdown_to_blog-0.4.7.dist-info/entry_points.txt
markdown_to_blog-0.4.7.dist-info/RECORD
