Metadata-Version: 2.3
Name: markdown-to-blog
Version: 0.4.7
Summary: Add your description here
Author-email: David Cho <csi00700@gmail.com>
Requires-Python: >=3.10
Requires-Dist: aiofiles>=24.1.0
Requires-Dist: aiohttp>=3.11.12
Requires-Dist: bs4>=0.0.2
Requires-Dist: click>=8.1.8
Requires-Dist: configobj>=5.0.9
Requires-Dist: cryptography>=42.0.0
Requires-Dist: google-api-python-client>=2.161.0
Requires-Dist: google-generativeai>=0.8.0
Requires-Dist: httplib2>=0.20.0
Requires-Dist: httpx>=0.28.1
Requires-Dist: images-upload-cli>=3.0.6
Requires-Dist: loguru>=0.7.3
Requires-Dist: markdown2>=2.5.3
Requires-Dist: markdownify>=0.11.6
Requires-Dist: oauth2client>=4.1.3
Requires-Dist: openai>=1.63.2
Requires-Dist: playwright>=1.40.0
Requires-Dist: pyairtable>=2.3.0
Requires-Dist: pyside6>=6.10.0
Requires-Dist: python-dotenv>=1.0.0
Requires-Dist: pyzmq>=26.0.0
Requires-Dist: textual>=2.0.4
Requires-Dist: thumbnail-maker>=0.1.10
Requires-Dist: tortoise-orm>=0.21.6
Requires-Dist: uv-easy>=0.2.5
